{
    "id": "BAS_DungeonConfigurator",
    "game": "Blade & Sorcery",
    "title": "DungeonConfigurator",
    "version": "v1.7",
    "dateLastUpdate": "2022-05-20",
    "links": {
      "nexus": "https://www.nexusmods.com/bladeandsorcery/mods/5032",
      "mirror": "https://drive.google.com/drive/folders/1cudAfFu67Y_2Pt8Z2BEWk8ttY2zRcnOS?usp=sharing",
      "source": "https://github.com/ficusmods/BAS_DungeonConfigurator"
    },
    "hasArticle": false,
    "articleID": "",
    "summary": "Allows configuring the type of enemies, the enemy number, player spells & inventory, and generator seed before embarking. Some of it's features can be used on any map."
}